duck_domain/__init__.py
duck_domain/core/crud/dtos/__init__.py
duck_domain/core/crud/dtos/create_dto.py
duck_domain/core/crud/dtos/include_dto.py
duck_domain/core/crud/dtos/update_dto.py
duck_domain/core/crud/dtos/validators/__init__.py
duck_domain/core/crud/dtos/validators/validate_bool_field.py
duck_domain/core/crud/dtos/validators/validate_null_or_field.py
duck_domain/core/crud/dtos/where_dto.py
duck_domain/core/crud/i_repository.py
duck_domain/core/errors/handdlers/app_error.py
duck_domain/core/handdlers/async_handler.py
duck_domain/core/handdlers/query_response.py
duck_domain/core/types/base_dto.py
duck_domain/core/types/null.py
duck_domain/core/types/null_or.py
duck_domain/core/types/request_dto.py
duck_domain/django_tools/__init__.py
duck_domain/django_tools/soft_delete/soft_delete_django_repository.py
duck_domain/django_tools/soft_delete/soft_delete_model.py
duck_domain-0.1.6.dist-info/METADATA
duck_domain-0.1.6.dist-info/WHEEL
duck_domain-0.1.6.dist-info/RECORD
