Metadata-Version: 2.3
Name: duck_domain
Version: 0.1.6
Summary: 
Author: Pato
Author-email: pheprogrammer@gmail.com
Requires-Python: >=3.10
Classifier: Programming Language :: Python :: 3
Classifier: Programming Language :: Python :: 3.10
Classifier: Programming Language :: Python :: 3.11
Classifier: Programming Language :: Python :: 3.12
Classifier: Programming Language :: Python :: 3.13
Provides-Extra: tests
Requires-Dist: django (>=5.2.6,<6.0.0)
Requires-Dist: djangorestframework (>=3.16.0,<4.0.0)
Requires-Dist: duck-django-soft-delete (>=0.1.5,<0.2.0)
Requires-Dist: pydantic (>=2.11.5,<3.0.0)
Project-URL: Homepage, https://pypi.org/project/duck_domain/
Project-URL: Repository, https://github.com/PheFreire/DuckDjangoDomain
